oauth2_client/__init__.py
oauth2_client/api_client.py
oauth2_client/api_client_async.py
oauth2_client/config.py
oauth2_client/exceptions.py
oauth2_client/token_manager.py
oauth2_client/token_manager_async.py
swift_oauth2_client-0.6.0.dist-info/LICENSE
swift_oauth2_client-0.6.0.dist-info/METADATA
swift_oauth2_client-0.6.0.dist-info/WHEEL
swift_oauth2_client-0.6.0.dist-info/RECORD
