Metadata-Version: 2.1
Name: swift-oauth2-client
Version: 0.6.0
Summary: Make authenticated API calls using OAuth2 in Python applications
Home-page: https://github.com/swiftsoftwaregroup/swift-oauth2-client
License: Apache-2.0
Author: Swift Software Group
Author-email: hello@swiftsoftwaregroup.com
Requires-Python: >=3.10,<4.0
Classifier: License :: OSI Approved :: Apache Software License
Classifier: Programming Language :: Python :: 3
Classifier: Programming Language :: Python :: 3.10
Classifier: Programming Language :: Python :: 3.11
Classifier: Programming Language :: Python :: 3.12
Requires-Dist: httpx (>=0.27.2,<0.28.0)
Project-URL: Documentation, https://swiftsoftwaregroup.github.io/swift-oauth2-client
Project-URL: Repository, https://github.com/swiftsoftwaregroup/swift-oauth2-client
